dub/__init__.py
dub/_hooks/__init__.py
dub/_hooks/registration.py
dub/_hooks/sdkhooks.py
dub/_hooks/types.py
dub/_version.py
dub/analytics.py
dub/basesdk.py
dub/commissions.py
dub/customers.py
dub/domains.py
dub/embed_tokens.py
dub/events.py
dub/folders.py
dub/httpclient.py
dub/links.py
dub/models/__init__.py
dub/models/components/__init__.py
dub/models/components/analyticsbrowsers.py
dub/models/components/analyticscities.py
dub/models/components/analyticscontinents.py
dub/models/components/analyticscount.py
dub/models/components/analyticscountries.py
dub/models/components/analyticsdevices.py
dub/models/components/analyticsos.py
dub/models/components/analyticsreferers.py
dub/models/components/analyticsrefererurls.py
dub/models/components/analyticsregions.py
dub/models/components/analyticstimeseries.py
dub/models/components/analyticstoplinks.py
dub/models/components/analyticstopurls.py
dub/models/components/analyticstriggers.py
dub/models/components/commissioncreatedevent.py
dub/models/components/domainschema.py
dub/models/components/folderschema.py
dub/models/components/leadcreatedevent.py
dub/models/components/linkclickedevent.py
dub/models/components/linkerrorschema.py
dub/models/components/linkschema.py
dub/models/components/linktagschema.py
dub/models/components/linktagschemaoutput.py
dub/models/components/linkwebhookevent.py
dub/models/components/partneranalyticscount.py
dub/models/components/partneranalyticstimeseries.py
dub/models/components/partneranalyticstoplinks.py
dub/models/components/partnerapplicationsubmittedevent.py
dub/models/components/partnerenrolledevent.py
dub/models/components/salecreatedevent.py
dub/models/components/security.py
dub/models/components/webhookevent.py
dub/models/components/workspaceschema.py
dub/models/errors/__init__.py
dub/models/errors/badrequest.py
dub/models/errors/conflict.py
dub/models/errors/duberror.py
dub/models/errors/forbidden.py
dub/models/errors/internalservererror.py
dub/models/errors/inviteexpired.py
dub-0.34.0.dist-info/METADATA
dub-0.34.0.dist-info/WHEEL
dub-0.34.0.dist-info/licenses/LICENSE
dub-0.34.0.dist-info/RECORD
